LICENSE.rst
MANIFEST.in
README.rst
setup.py
blockage/__init__.py
blockage/plugins.py
blockage/tests.py
nose_blockage.egg-info/PKG-INFO
nose_blockage.egg-info/SOURCES.txt
nose_blockage.egg-info/dependency_links.txt
nose_blockage.egg-info/entry_points.txt
nose_blockage.egg-info/not-zip-safe
nose_blockage.egg-info/requires.txt
nose_blockage.egg-info/top_level.txt