Metadata-Version: 1.0
Name: nose-blockage
Version: 0.1.2
Summary: Raise errors when communicating outside of tests
Home-page: https://github.com/andymckay/nose-blockage
Author: Andy McKay
Author-email: andym@mozilla.com
License: BSD
Platform: UNKNOWN
Classifier: Intended Audience :: Developers
Classifier: Natural Language :: English
Classifier: Operating System :: OS Independent
Classifier: Framework :: Django
